sagalogger
