Metadata-Version: 1.0
Name: sagalogger
Version: 0.3.3
Summary: A json log formatter.
Home-page: https://www.github.com/Sagacify/logger-py
Author: Sagacify
Author-email: dev+python@sagacify.com
License: MIT
Platform: UNKNOWN
